{
    "BACKGROUND": [
        [
            0,
            0,
            0
        ]
    ],
    "COMMENT": [
        [
            255,
            0,
            0
        ],
        [
            244,
            0,
            0
        ]
    ],
    "DECORATION": [
        [
            0,
            255,
            0
        ]
    ],
    "COMMENT_AND_DECORATION": [
        [
            255,
            255,
            0
        ]
    ],
    "MAINTEXT": [
        [
            0,
            0,
            255
        ]
    ],
    "COMMENT_AND_MAINTEXT": [
        [
            255,
            0,
            255
        ]
    ],
    "MAINTEXT_AND_DECORATION": [
        [
            0,
            255,
            255
        ]
    ],
    "MAINTEXT_AND_DECORATION_AND_COMMENT": [
        [
            255,
            255,
            255
        ]
    ],
    "ASCENDER": [
        [
            250,
            120,
            120
        ]
    ],
    "XREGION": [
        [
            120,
            250,
            120
        ]
    ],
    "DESCENDER": [
        [
            120,
            120,
            250
        ]
    ],
    "BASELINE": [
        [
            30,
            100,
            200
        ]
    ],
    "TOPLINE": [
        [
            100,
            30,
            200
        ]
    ],
    "HEAD": [
        [
            100,
            100,
            100
        ]
    ],
    "TAIL": [
        [
            100,
            100,
            100
        ]
    ],
    "TEXT_REGION": [
        [
            100,
            100,
            100
        ]
    ]
}